CHANGES.txt
LICENSE.txt
MANIFEST.in
README.txt
VERSION.txt
alembic.ini
development.ini
docs_build.sh
i18n.sh
production.ini
setup.cfg
setup.py
test.ini
upgrade_db.sh
alembic/README
alembic/env.py
alembic/env.py.orig
alembic/env.pyc
alembic/script.py.mako
alembic/versions/04f33a9d75b5_alter_db.py
alembic/versions/0dde2b383d6b_alter_db.py
alembic/versions/106f13073959_alter_db.py
alembic/versions/309c8478ded6_alter_db.py
alembic/versions/735cec8a7bc0_alter_db.py
alembic/versions/9d6e4f7a0f93_alter_db.py
alembic/versions/b1eac8a9f577_alter_db.py
alembic/versions/c38723878dbe_alter_db.py
alembic/versions/d115817efcba_alter_db.py
alembic/versions/d6bfdd337869_alter_db.py
alembic/versions/d73a81056977_alter_db.py
alembic/versions/d9b134d71b1f_alter_db.py
alembic/versions/db9e3d6db63c_alter_db.py
alembic/versions/dccf36ae49e4_alter_db.py
alembic/versions/deff2700efc6_alter_db.py
data/storage/no-image.png
data/storage/2015627/05a68187-5992-47e9-89d2-ff87ef582df7.jpg
data/storage/2015627/0c0fe5ca-f9b6-4abe-9eef-075b5f9cc77b.jpg
data/storage/2015627/0e4b4266-5a88-4597-b313-716811b567a4.jpg
data/storage/2015627/11fad20d-91e8-4aae-9991-84a9f3ce68a2.jpg
data/storage/2015627/17da5860-be6a-4ae8-8dcd-999e02a544bf.png
data/storage/2015627/2617f308-d686-4331-bc6f-80bc676aea4f.jpg
data/storage/2015627/29b619df-45cd-4e66-b22f-0dfada386f35.jpg
data/storage/2015627/4336de82-c2a6-4d13-a773-13af4ccbd631.jpg
data/storage/2015627/46f5b1f1-2951-4246-a5c1-34a5a454cffc.jpg
data/storage/2015627/5f588c0b-bd08-4f4e-a55e-54f76895a184.png
data/storage/2015627/64d46808-2e69-4048-bc60-ca7ee03de0de.pdf
data/storage/2015627/6df3bd9c-3b88-4d9e-9679-ea8ca0cf85b5.jpg
data/storage/2015627/790cd030-03b7-474b-9b24-435dadda5531.jpg
data/storage/2015627/8499239c-ae10-489b-a458-c4f852a49ace.jpg
data/storage/2015627/8c985058-a198-42df-97d2-f55996a1a9b3.jpg
data/storage/2015627/8cd83c11-92dd-4eee-b9a7-15d5f17feb09.jpg
data/storage/2015627/980c9b29-8007-441b-8917-87fcf4a3132b.jpg
travelcrm.egg-info/PKG-INFO
travelcrm.egg-info/SOURCES.txt
travelcrm.egg-info/dependency_links.txt
travelcrm.egg-info/entry_points.txt
travelcrm.egg-info/not-zip-safe
travelcrm.egg-info/requires.txt
travelcrm.egg-info/top_level.txt
