Metadata-Version: 1.1
Name: travelcrm
Version: 0.6.5b1
Summary: travelcrm
Home-page: http://www.travelcrm.org.ua
Author: Vitalii Mazur
Author-email: vitalii.mazur@gmail.com
License: UNKNOWN
Keywords: web wsgi bfg pylons pyramid travel crms
Platform: UNKNOWN
Classifier: Programming Language :: Python
Classifier: Framework :: Pyramid
Classifier: Topic :: Internet :: WWW/HTTP
Classifier: Topic :: Internet :: WWW/HTTP :: WSGI :: Application
